app/add.py
poetry_group_dependency-0.1.0.dist-info/METADATA
poetry_group_dependency-0.1.0.dist-info/WHEEL
poetry_group_dependency-0.1.0.dist-info/RECORD
